kradle/__init__.py
kradle/agent.py
kradle/agent_like.py
kradle/agent_manager.py
kradle/contexts.py
kradle/core.py
kradle/experiment.py
kradle/kradle.py
kradle/logger.py
kradle/mc.py
kradle/models.py
kradle/py.typed
kradle/ssh_tunnel.py
kradle/api/__init__.py
kradle/api/client.py
kradle/api/http.py
kradle/api/resources/__init__.py
kradle/api/resources/agent.py
kradle/api/resources/challenge.py
kradle/api/resources/human.py
kradle/api/resources/log.py
kradle/api/resources/run.py
kradle/memory/__init__.py
kradle-0.8.3.dist-info/METADATA
kradle-0.8.3.dist-info/WHEEL
kradle-0.8.3.dist-info/top_level.txt
kradle-0.8.3.dist-info/RECORD
