Metadata-Version: 2.4
Name: kradle
Version: 0.8.3
Summary: Create AI agents that play Minecraft with Kradle
Author-email: Kradle Team <humans@kradle.ai>
Project-URL: Homepage, https://github.com/Kradle-ai/kradle-python
Project-URL: Bug Tracker, https://github.com/Kradle-ai/kradle-python/issues
Classifier: Programming Language :: Python :: 3
Classifier: License :: OSI Approved :: MIT License
Classifier: Operating System :: OS Independent
Requires-Python: >=3.9
Requires-Dist: flask
Requires-Dist: flask-cors
Requires-Dist: rich
Requires-Dist: anthropic
Requires-Dist: openai
Requires-Dist: python-dotenv
Requires-Dist: requests
Requires-Dist: psutil
Requires-Dist: redis
Requires-Dist: google-cloud-firestore
Requires-Dist: watchdog
